thmapi/__init__.py
thmapi/auth.py
thmapi/instance.py
thmapi/koth.py
thmapi/leaderboard.py
thmapi/room.py
thmapi/stats.py
thmapi/team.py
thmapi/thm.py
thmapi/user.py
thmapi/util.py
thmapi/vpn.py
thmapi-0.11.1.dist-info/LICENSE
thmapi-0.11.1.dist-info/METADATA
thmapi-0.11.1.dist-info/WHEEL
thmapi-0.11.1.dist-info/top_level.txt
thmapi-0.11.1.dist-info/RECORD
